voice_mode/__init__.py
voice_mode/__main__.py
voice_mode/__version__.py
voice_mode/cli.py
voice_mode/config.py
voice_mode/conversation_logger.py
voice_mode/core.py
voice_mode/provider_discovery.py
voice_mode/providers.py
voice_mode/server.py
voice_mode/shared.py
voice_mode/statistics.py
voice_mode/streaming.py
voice_mode/voice_preferences.py
voice_mode/prompts/README.md
voice_mode/prompts/__init__.py
voice_mode/prompts/conversation.py
voice_mode/prompts/kokoro_management.py
voice_mode/prompts/show_and_tell.py
voice_mode/prompts/status.py
voice_mode/prompts/voice_commands.py
voice_mode/resources/__init__.py
voice_mode/resources/audio_files.py
voice_mode/resources/statistics.py
voice_mode/tools/__init__.py
voice_mode/tools/conversation.py
voice_mode/tools/dependencies.py
voice_mode/tools/devices.py
voice_mode/tools/diagnostics.py
voice_mode/tools/livekit.py
voice_mode/tools/providers.py
voice_mode/tools/services.py
voice_mode/tools/statistics.py
voice_mode/tools/synthesis.py
voice_mode/tools/transcription.py
voice_mode/utils/__init__.py
voice_mode/utils/audio_diagnostics.py
voice_mode/utils/event_logger.py
voice_mode/utils/ffmpeg_check.py
voice_mode/utils/format_migration.py
voice_mode_azure-2.13.0.dist-info/METADATA
voice_mode_azure-2.13.0.dist-info/WHEEL
voice_mode_azure-2.13.0.dist-info/entry_points.txt
voice_mode_azure-2.13.0.dist-info/RECORD
